{
  "success": true,
  "error": null,
  "results": {
    "detectors": [
      {
        "elements": [
          {
            "type": "variable",
            "name": "owner",
            "source_mapping": {
              "start": 8068,
              "length": 13,
              "filename_relative": "BOBAMASK.sol",
              "filename_absolute": "D:/CSE487 - PAPER/Dataset/raw_data/0x444fd826977d02a509c28d3cdfab853ac196199f/BOBAMASK.sol",
              "filename_short": "BOBAMASK.sol",
              "is_dependency": false,
              "lines": [
                455
              ],
              "starting_column": 24,
              "ending_column": 37
            },
            "type_specific_fields": {
              "parent": {
                "type": "function",
                "name": "allowance",
                "source_mapping": {
                  "start": 8049,
                  "length": 145,
                  "filename_relative": "BOBAMASK.sol",
                  "filename_absolute": "D:/CSE487 - PAPER/Dataset/raw_data/0x444fd826977d02a509c28d3cdfab853ac196199f/BOBAMASK.sol",
                  "filename_short": "BOBAMASK.sol",
                  "is_dependency": false,
                  "lines": [
                    455,
                    456,
                    457,
                    458,
                    459
                  ],
                  "starting_column": 5,
                  "ending_column": 6
                },
                "type_specific_fields": {
                  "parent": {
                    "type": "contract",
                    "name": "BOBAMASK",
                    "source_mapping": {
                      "start": 6746,
                      "length": 2871,
                      "filename_relative": "BOBAMASK.sol",
                      "filename_absolute": "D:/CSE487 - PAPER/Dataset/raw_data/0x444fd826977d02a509c28d3cdfab853ac196199f/BOBAMASK.sol",
                      "filename_short": "BOBAMASK.sol",
                      "is_dependency": false,
                      "lines": [
                        381,
                        382,
                        383,
                        384,
                        385,
                        386,
                        387,
                        388,
                        389,
                        390,
                        391,
                        392,
                        393,
                        394,
                        395,
                        396,
                        397,
                        398,
                        399,
                        400,
                        401,
                        402,
                        403,
                        404,
                        405,
                        406,
                        407,
                        408,
                        409,
                        410,
                        411,
                        412,
                        413,
                        414,
                        415,
                        416,
                        417,
                        418,
                        419,
                        420,
                        421,
                        422,
                        423,
                        424,
                        425,
                        426,
                        427,
                        428,
                        429,
                        430,
                        431,
                        432,
                        433,
                        434,
                        435,
                        436,
                        437,
                        438,
                        439,
                        440,
                        441,
                        442,
                        443,
                        444,
                        445,
                        446,
                        447,
                        448,
                        449,
                        450,
                        451,
                        452,
                        453,
                        454,
                        455,
                        456,
                        457,
                        458,
                        459,
                        460,
                        461,
                        462,
                        463,
                        464,
                        465,
                        466,
                        467,
                        468,
                        469,
                        470,
                        471,
                        472,
                        473,
                        474,
                        475,
                        476,
                        477,
                        478,
                        479,
                        480,
                        481,
                        482,
                        483,
                        484,
                        485,
                        486,
                        487,
                        488,
                        489,
                        490,
                        491,
                        492,
                        493,
                        494,
                        495,
                        496,
                        497,
                        498,
                        499,
                        500,
                        501,
                        502,
                        503,
                        504,
                        505,
                        506,
                        507,
                        508,
                        509,
                        510,
                        511,
                        512,
                        513,
                        514,
                        515,
                        516,
                        517,
                        518,
                        519,
                        520,
                        521,
                        522,
                        523,
                        524,
                        525,
                        526,
                        527,
                        528
                      ],
                      "starting_column": 1,
                      "ending_column": 0
                    }
                  },
                  "signature": "allowance(address,address)"
                }
              }
            }
          },
          {
            "type": "function",
            "name": "owner",
            "source_mapping": {
              "start": 6062,
              "length": 81,
              "filename_relative": "BOBAMASK.sol",
              "filename_absolute": "D:/CSE487 - PAPER/Dataset/raw_data/0x444fd826977d02a509c28d3cdfab853ac196199f/BOBAMASK.sol",
              "filename_short": "BOBAMASK.sol",
              "is_dependency": false,
              "lines": [
                337,
                338,
                339,
                340,
                341
              ],
              "starting_column": 5,
              "ending_column": 6
            },
            "type_specific_fields": {
              "parent": {
                "type": "contract",
                "name": "Ownable",
                "source_mapping": {
                  "start": 5722,
                  "length": 1018,
                  "filename_relative": "BOBAMASK.sol",
                  "filename_absolute": "D:/CSE487 - PAPER/Dataset/raw_data/0x444fd826977d02a509c28d3cdfab853ac196199f/BOBAMASK.sol",
                  "filename_short": "BOBAMASK.sol",
                  "is_dependency": false,
                  "lines": [
                    315,
                    316,
                    317,
                    318,
                    319,
                    320,
                    321,
                    322,
                    323,
                    324,
                    325,
                    326,
                    327,
                    328,
                    329,
                    330,
                    331,
                    332,
                    333,
                    334,
                    335,
                    336,
                    337,
                    338,
                    339,
                    340,
                    341,
                    342,
                    343,
                    344,
                    345,
                    346,
                    347,
                    348,
                    349,
                    350,
                    351,
                    352,
                    353,
                    354,
                    355,
                    356,
                    357,
                    358,
                    359,
                    360,
                    361,
                    362,
                    363,
                    364,
                    365,
                    366,
                    367,
                    368,
                    369,
                    370,
                    371,
                    372,
                    373,
                    374,
                    375,
                    376,
                    377
                  ],
                  "starting_column": 1,
                  "ending_column": 2
                }
              },
              "signature": "owner()"
            }
          }
        ],
        "description": "BOBAMASK.allowance(address,address).owner (BOBAMASK.sol#455) shadows:\n\t- Ownable.owner() (BOBAMASK.sol#337-341) (function)\n",
        "markdown": "[BOBAMASK.allowance(address,address).owner](BOBAMASK.sol#L455) shadows:\n\t- [Ownable.owner()](BOBAMASK.sol#L337-L341) (function)\n",
        "first_markdown_element": "BOBAMASK.sol#L455",
        "id": "20c007081ee8db09f3f9907470f3ce2fe22045785df334b2fe51d24bb9598faf",
        "check": "shadowing-local",
        "impact": "Low",
        "confidence": "High"
      },
      {
        "elements": [
          {
            "type": "function",
            "name": "isContract",
            "source_mapping": {
              "start": 922,
              "length": 380,
              "filename_relative": "BOBAMASK.sol",
              "filename_absolute": "D:/CSE487 - PAPER/Dataset/raw_data/0x444fd826977d02a509c28d3cdfab853ac196199f/BOBAMASK.sol",
              "filename_short": "BOBAMASK.sol",
              "is_dependency": false,
              "lines": [
                69,
                70,
                71,
                72,
                73,
                74,
                75,
                76,
                77,
                78,
                79,
                80,
                81
              ],
              "starting_column": 5,
              "ending_column": 6
            },
            "type_specific_fields": {
              "parent": {
                "type": "contract",
                "name": "Address",
                "source_mapping": {
                  "start": 891,
                  "length": 2803,
                  "filename_relative": "BOBAMASK.sol",
                  "filename_absolute": "D:/CSE487 - PAPER/Dataset/raw_data/0x444fd826977d02a509c28d3cdfab853ac196199f/BOBAMASK.sol",
                  "filename_short": "BOBAMASK.sol",
                  "is_dependency": false,
                  "lines": [
                    65,
                    66,
                    67,
                    68,
                    69,
                    70,
                    71,
                    72,
                    73,
                    74,
                    75,
                    76,
                    77,
                    78,
                    79,
                    80,
                    81,
                    82,
                    83,
                    84,
                    85,
                    86,
                    87,
                    88,
                    89,
                    90,
                    91,
                    92,
                    93,
                    94,
                    95,
                    96,
                    97,
                    98,
                    99,
                    100,
                    101,
                    102,
                    103,
                    104,
                    105,
                    106,
                    107,
                    108,
                    109,
                    110,
                    111,
                    112,
                    113,
                    114,
                    115,
                    116,
                    117,
                    118,
                    119,
                    120,
                    121,
                    122,
                    123,
                    124,
                    125,
                    126,
                    127,
                    128,
                    129,
                    130,
                    131,
                    132,
                    133,
                    134,
                    135,
                    136,
                    137,
                    138,
                    139,
                    140,
                    141,
                    142,
                    143,
                    144,
                    145,
                    146,
                    147,
                    148,
                    149,
                    150,
                    151,
                    152,
                    153,
                    154,
                    155,
                    156,
                    157,
                    158,
                    159,
                    160,
                    161,
                    162,
                    163,
                    164,
                    165,
                    166,
                    167,
                    168,
                    169,
                    170,
                    171,
                    172,
                    173,
                    174,
                    175,
                    176,
                    177,
                    178,
                    179
                  ],
                  "starting_column": 1,
                  "ending_column": 2
                }
              },
              "signature": "isContract(address)"
            }
          },
          {
            "type": "node",
            "name": "",
            "source_mapping": {
              "start": 1186,
              "length": 45,
              "filename_relative": "BOBAMASK.sol",
              "filename_absolute": "D:/CSE487 - PAPER/Dataset/raw_data/0x444fd826977d02a509c28d3cdfab853ac196199f/BOBAMASK.sol",
              "filename_short": "BOBAMASK.sol",
              "is_dependency": false,
              "lines": [
                77
              ],
              "starting_column": 9,
              "ending_column": 54
            },
            "type_specific_fields": {
              "parent": {
                "type": "function",
                "name": "isContract",
                "source_mapping": {
                  "start": 922,
                  "length": 380,
                  "filename_relative": "BOBAMASK.sol",
                  "filename_absolute": "D:/CSE487 - PAPER/Dataset/raw_data/0x444fd826977d02a509c28d3cdfab853ac196199f/BOBAMASK.sol",
                  "filename_short": "BOBAMASK.sol",
                  "is_dependency": false,
                  "lines": [
                    69,
                    70,
                    71,
                    72,
                    73,
                    74,
                    75,
                    76,
                    77,
                    78,
                    79,
                    80,
                    81
                  ],
                  "starting_column": 5,
                  "ending_column": 6
                },
                "type_specific_fields": {
                  "parent": {
                    "type": "contract",
                    "name": "Address",
                    "source_mapping": {
                      "start": 891,
                      "length": 2803,
                      "filename_relative": "BOBAMASK.sol",
                      "filename_absolute": "D:/CSE487 - PAPER/Dataset/raw_data/0x444fd826977d02a509c28d3cdfab853ac196199f/BOBAMASK.sol",
                      "filename_short": "BOBAMASK.sol",
                      "is_dependency": false,
                      "lines": [
                        65,
                        66,
                        67,
                        68,
                        69,
                        70,
                        71,
                        72,
                        73,
                        74,
                        75,
                        76,
                        77,
                        78,
                        79,
                        80,
                        81,
                        82,
                        83,
                        84,
                        85,
                        86,
                        87,
                        88,
                        89,
                        90,
                        91,
                        92,
                        93,
                        94,
                        95,
                        96,
                        97,
                        98,
                        99,
                        100,
                        101,
                        102,
                        103,
                        104,
                        105,
                        106,
                        107,
                        108,
                        109,
                        110,
                        111,
                        112,
                        113,
                        114,
                        115,
                        116,
                        117,
                        118,
                        119,
                        120,
                        121,
                        122,
                        123,
                        124,
                        125,
                        126,
                        127,
                        128,
                        129,
                        130,
                        131,
                        132,
                        133,
                        134,
                        135,
                        136,
                        137,
                        138,
                        139,
                        140,
                        141,
                        142,
                        143,
                        144,
                        145,
                        146,
                        147,
                        148,
                        149,
                        150,
                        151,
                        152,
                        153,
                        154,
                        155,
                        156,
                        157,
                        158,
                        159,
                        160,
                        161,
                        162,
                        163,
                        164,
                        165,
                        166,
                        167,
                        168,
                        169,
                        170,
                        171,
                        172,
                        173,
                        174,
                        175,
                        176,
                        177,
                        178,
                        179
                      ],
                      "starting_column": 1,
                      "ending_column": 2
                    }
                  },
                  "signature": "isContract(address)"
                }
              }
            }
          }
        ],
        "description": "Address.isContract(address) (BOBAMASK.sol#69-81) uses assembly\n\t- INLINE ASM (BOBAMASK.sol#77)\n",
        "markdown": "[Address.isContract(address)](BOBAMASK.sol#L69-L81) uses assembly\n\t- [INLINE ASM](BOBAMASK.sol#L77)\n",
        "first_markdown_element": "BOBAMASK.sol#L69-L81",
        "id": "4a0abd2ac6e7df093b3310a1d2fa07d61fd6ddb15d8cfbd04cd66b6275ef54e1",
        "check": "assembly",
        "impact": "Informational",
        "confidence": "High"
      },
      {
        "elements": [
          {
            "type": "function",
            "name": "_functionCallWithValue",
            "source_mapping": {
              "start": 2690,
              "length": 1000,
              "filename_relative": "BOBAMASK.sol",
              "filename_absolute": "D:/CSE487 - PAPER/Dataset/raw_data/0x444fd826977d02a509c28d3cdfab853ac196199f/BOBAMASK.sol",
              "filename_short": "BOBAMASK.sol",
              "is_dependency": false,
              "lines": [
                135,
                136,
                137,
                138,
                139,
                140,
                141,
                142,
                143,
                144,
                145,
                146,
                147,
                148,
                149,
                150,
                151,
                152,
                153,
                154,
                155,
                156,
                157,
                158,
                159,
                160,
                161,
                162,
                163,
                164,
                165,
                166,
                167,
                168,
                169,
                170,
                171,
                172,
                173,
                174,
                175,
                176,
                177
              ],
              "starting_column": 5,
              "ending_column": 6
            },
            "type_specific_fields": {
              "parent": {
                "type": "contract",
                "name": "Address",
                "source_mapping": {
                  "start": 891,
                  "length": 2803,
                  "filename_relative": "BOBAMASK.sol",
                  "filename_absolute": "D:/CSE487 - PAPER/Dataset/raw_data/0x444fd826977d02a509c28d3cdfab853ac196199f/BOBAMASK.sol",
                  "filename_short": "BOBAMASK.sol",
                  "is_dependency": false,
                  "lines": [
                    65,
                    66,
                    67,
                    68,
                    69,
                    70,
                    71,
                    72,
                    73,
                    74,
                    75,
                    76,
                    77,
                    78,
                    79,
                    80,
                    81,
                    82,
                    83,
                    84,
                    85,
                    86,
                    87,
                    88,
                    89,
                    90,
                    91,
                    92,
                    93,
                    94,
                    95,
                    96,
                    97,
                    98,
                    99,
                    100,
                    101,
                    102,
                    103,
                    104,
                    105,
                    106,
                    107,
                    108,
                    109,
                    110,
                    111,
                    112,
                    113,
                    114,
                    115,
                    116,
                    117,
                    118,
                    119,
                    120,
                    121,
                    122,
                    123,
                    124,
                    125,
                    126,
                    127,
                    128,
                    129,
                    130,
                    131,
                    132,
                    133,
                    134,
                    135,
                    136,
                    137,
                    138,
                    139,
                    140,
                    141,
                    142,
                    143,
                    144,
                    145,
                    146,
                    147,
                    148,
                    149,
                    150,
                    151,
                    152,
                    153,
                    154,
                    155,
                    156,
                    157,
                    158,
                    159,
                    160,
                    161,
                    162,
                    163,
                    164,
                    165,
                    166,
                    167,
                    168,
                    169,
                    170,
                    171,
                    172,
                    173,
                    174,
                    175,
                    176,
                    177,
                    178,
                    179
                  ],
                  "starting_column": 1,
                  "ending_column": 2
                }
              },
              "signature": "_functionCallWithValue(address,bytes,uint256,string)"
            }
          },
          {
            "type": "node",
            "name": "",
            "source_mapping": {
              "start": 3431,
              "length": 160,
              "filename_relative": "BOBAMASK.sol",
              "filename_absolute": "D:/CSE487 - PAPER/Dataset/raw_data/0x444fd826977d02a509c28d3cdfab853ac196199f/BOBAMASK.sol",
              "filename_short": "BOBAMASK.sol",
              "is_dependency": false,
              "lines": [
                161,
                162,
                163,
                164,
                165,
                166,
                167
              ],
              "starting_column": 17,
              "ending_column": 18
            },
            "type_specific_fields": {
              "parent": {
                "type": "function",
                "name": "_functionCallWithValue",
                "source_mapping": {
                  "start": 2690,
                  "length": 1000,
                  "filename_relative": "BOBAMASK.sol",
                  "filename_absolute": "D:/CSE487 - PAPER/Dataset/raw_data/0x444fd826977d02a509c28d3cdfab853ac196199f/BOBAMASK.sol",
                  "filename_short": "BOBAMASK.sol",
                  "is_dependency": false,
                  "lines": [
                    135,
                    136,
                    137,
                    138,
                    139,
                    140,
                    141,
                    142,
                    143,
                    144,
                    145,
                    146,
                    147,
                    148,
                    149,
                    150,
                    151,
                    152,
                    153,
                    154,
                    155,
                    156,
                    157,
                    158,
                    159,
                    160,
                    161,
                    162,
                    163,
                    164,
                    165,
                    166,
                    167,
                    168,
                    169,
                    170,
                    171,
                    172,
                    173,
                    174,
                    175,
                    176,
                    177
                  ],
                  "starting_column": 5,
                  "ending_column": 6
                },
                "type_specific_fields": {
                  "parent": {
                    "type": "contract",
                    "name": "Address",
                    "source_mapping": {
                      "start": 891,
                      "length": 2803,
                      "filename_relative": "BOBAMASK.sol",
                      "filename_absolute": "D:/CSE487 - PAPER/Dataset/raw_data/0x444fd826977d02a509c28d3cdfab853ac196199f/BOBAMASK.sol",
                      "filename_short": "BOBAMASK.sol",
                      "is_dependency": false,
                      "lines": [
                        65,
                        66,
                        67,
                        68,
                        69,
                        70,
                        71,
                        72,
                        73,
                        74,
                        75,
                        76,
                        77,
                        78,
                        79,
                        80,
                        81,
                        82,
                        83,
                        84,
                        85,
                        86,
                        87,
                        88,
                        89,
                        90,
                        91,
                        92,
                        93,
                        94,
                        95,
                        96,
                        97,
                        98,
                        99,
                        100,
                        101,
                        102,
                        103,
                        104,
                        105,
                        106,
                        107,
                        108,
                        109,
                        110,
                        111,
                        112,
                        113,
                        114,
                        115,
                        116,
                        117,
                        118,
                        119,
                        120,
                        121,
                        122,
                        123,
                        124,
                        125,
                        126,
                        127,
                        128,
                        129,
                        130,
                        131,
                        132,
                        133,
                        134,
                        135,
                        136,
                        137,
                        138,
                        139,
                        140,
                        141,
                        142,
                        143,
                        144,
                        145,
                        146,
                        147,
                        148,
                        149,
                        150,
                        151,
                        152,
                        153,
                        154,
                        155,
                        156,
                        157,
                        158,
                        159,
                        160,
                        161,
                        162,
                        163,
                        164,
                        165,
                        166,
                        167,
                        168,
                        169,
                        170,
                        171,
                        172,
                        173,
                        174,
                        175,
                        176,
                        177,
                        178,
                        179
                      ],
                      "starting_column": 1,
                      "ending_column": 2
                    }
                  },
                  "signature": "_functionCallWithValue(address,bytes,uint256,string)"
                }
              }
            }
          }
        ],
        "description": "Address._functionCallWithValue(address,bytes,uint256,string) (BOBAMASK.sol#135-177) uses assembly\n\t- INLINE ASM (BOBAMASK.sol#161-167)\n",
        "markdown": "[Address._functionCallWithValue(address,bytes,uint256,string)](BOBAMASK.sol#L135-L177) uses assembly\n\t- [INLINE ASM](BOBAMASK.sol#L161-L167)\n",
        "first_markdown_element": "BOBAMASK.sol#L135-L177",
        "id": "533f6aa4b807adf3259579e50aa5bad8f6ee8e18e7a4561f56e790fa90e3ba53",
        "check": "assembly",
        "impact": "Informational",
        "confidence": "High"
      },
      {
        "elements": [
          {
            "type": "function",
            "name": "transferOwnership",
            "source_mapping": {
              "start": 6314,
              "length": 241,
              "filename_relative": "BOBAMASK.sol",
              "filename_absolute": "D:/CSE487 - PAPER/Dataset/raw_data/0x444fd826977d02a509c28d3cdfab853ac196199f/BOBAMASK.sol",
              "filename_short": "BOBAMASK.sol",
              "is_dependency": false,
              "lines": [
                355,
                356,
                357,
                358,
                359,
                360,
                361,
                362,
                363
              ],
              "starting_column": 5,
              "ending_column": 6
            },
            "type_specific_fields": {
              "parent": {
                "type": "contract",
                "name": "Ownable",
                "source_mapping": {
                  "start": 5722,
                  "length": 1018,
                  "filename_relative": "BOBAMASK.sol",
                  "filename_absolute": "D:/CSE487 - PAPER/Dataset/raw_data/0x444fd826977d02a509c28d3cdfab853ac196199f/BOBAMASK.sol",
                  "filename_short": "BOBAMASK.sol",
                  "is_dependency": false,
                  "lines": [
                    315,
                    316,
                    317,
                    318,
                    319,
                    320,
                    321,
                    322,
                    323,
                    324,
                    325,
                    326,
                    327,
                    328,
                    329,
                    330,
                    331,
                    332,
                    333,
                    334,
                    335,
                    336,
                    337,
                    338,
                    339,
                    340,
                    341,
                    342,
                    343,
                    344,
                    345,
                    346,
                    347,
                    348,
                    349,
                    350,
                    351,
                    352,
                    353,
                    354,
                    355,
                    356,
                    357,
                    358,
                    359,
                    360,
                    361,
                    362,
                    363,
                    364,
                    365,
                    366,
                    367,
                    368,
                    369,
                    370,
                    371,
                    372,
                    373,
                    374,
                    375,
                    376,
                    377
                  ],
                  "starting_column": 1,
                  "ending_column": 2
                }
              },
              "signature": "transferOwnership(address)"
            }
          }
        ],
        "description": "Ownable.transferOwnership(address) (BOBAMASK.sol#355-363) is never used and should be removed\n",
        "markdown": "[Ownable.transferOwnership(address)](BOBAMASK.sol#L355-L363) is never used and should be removed\n",
        "first_markdown_element": "BOBAMASK.sol#L355-L363",
        "id": "498dbedb4721929363c53c7f2d623f7ea6b2ab87895d623ea3914300a4f27138",
        "check": "dead-code",
        "impact": "Informational",
        "confidence": "Medium"
      },
      {
        "elements": [
          {
            "type": "function",
            "name": "_msgData",
            "source_mapping": {
              "start": 5476,
              "length": 236,
              "filename_relative": "BOBAMASK.sol",
              "filename_absolute": "D:/CSE487 - PAPER/Dataset/raw_data/0x444fd826977d02a509c28d3cdfab853ac196199f/BOBAMASK.sol",
              "filename_short": "BOBAMASK.sol",
              "is_dependency": false,
              "lines": [
                303,
                304,
                305,
                306,
                307,
                308,
                309
              ],
              "starting_column": 5,
              "ending_column": 6
            },
            "type_specific_fields": {
              "parent": {
                "type": "contract",
                "name": "Context",
                "source_mapping": {
                  "start": 5317,
                  "length": 399,
                  "filename_relative": "BOBAMASK.sol",
                  "filename_absolute": "D:/CSE487 - PAPER/Dataset/raw_data/0x444fd826977d02a509c28d3cdfab853ac196199f/BOBAMASK.sol",
                  "filename_short": "BOBAMASK.sol",
                  "is_dependency": false,
                  "lines": [
                    291,
                    292,
                    293,
                    294,
                    295,
                    296,
                    297,
                    298,
                    299,
                    300,
                    301,
                    302,
                    303,
                    304,
                    305,
                    306,
                    307,
                    308,
                    309,
                    310,
                    311
                  ],
                  "starting_column": 1,
                  "ending_column": 2
                }
              },
              "signature": "_msgData()"
            }
          }
        ],
        "description": "Context._msgData() (BOBAMASK.sol#303-309) is never used and should be removed\n",
        "markdown": "[Context._msgData()](BOBAMASK.sol#L303-L309) is never used and should be removed\n",
        "first_markdown_element": "BOBAMASK.sol#L303-L309",
        "id": "93bd23634a3bf022810e43138345cf58db61248a704a7d277c8ec3d68c3ad188",
        "check": "dead-code",
        "impact": "Informational",
        "confidence": "Medium"
      },
      {
        "elements": [
          {
            "type": "variable",
            "name": "newComer",
            "source_mapping": {
              "start": 6565,
              "length": 39,
              "filename_relative": "BOBAMASK.sol",
              "filename_absolute": "D:/CSE487 - PAPER/Dataset/raw_data/0x444fd826977d02a509c28d3cdfab853ac196199f/BOBAMASK.sol",
              "filename_short": "BOBAMASK.sol",
              "is_dependency": false,
              "lines": [
                367
              ],
              "starting_column": 5,
              "ending_column": 44
            },
            "type_specific_fields": {
              "parent": {
                "type": "contract",
                "name": "Ownable",
                "source_mapping": {
                  "start": 5722,
                  "length": 1018,
                  "filename_relative": "BOBAMASK.sol",
                  "filename_absolute": "D:/CSE487 - PAPER/Dataset/raw_data/0x444fd826977d02a509c28d3cdfab853ac196199f/BOBAMASK.sol",
                  "filename_short": "BOBAMASK.sol",
                  "is_dependency": false,
                  "lines": [
                    315,
                    316,
                    317,
                    318,
                    319,
                    320,
                    321,
                    322,
                    323,
                    324,
                    325,
                    326,
                    327,
                    328,
                    329,
                    330,
                    331,
                    332,
                    333,
                    334,
                    335,
                    336,
                    337,
                    338,
                    339,
                    340,
                    341,
                    342,
                    343,
                    344,
                    345,
                    346,
                    347,
                    348,
                    349,
                    350,
                    351,
                    352,
                    353,
                    354,
                    355,
                    356,
                    357,
                    358,
                    359,
                    360,
                    361,
                    362,
                    363,
                    364,
                    365,
                    366,
                    367,
                    368,
                    369,
                    370,
                    371,
                    372,
                    373,
                    374,
                    375,
                    376,
                    377
                  ],
                  "starting_column": 1,
                  "ending_column": 2
                }
              }
            }
          }
        ],
        "description": "Ownable.newComer (BOBAMASK.sol#367) is set pre-construction with a non-constant function or state variable:\n\t- _msgSender()\n",
        "markdown": "[Ownable.newComer](BOBAMASK.sol#L367) is set pre-construction with a non-constant function or state variable:\n\t- _msgSender()\n",
        "first_markdown_element": "BOBAMASK.sol#L367",
        "id": "cdbb7cbf50635af90d395c465c02c4eb0bb818ff1fe648da6d13fd8cd6be17da",
        "check": "function-init-state",
        "impact": "Informational",
        "confidence": "High"
      },
      {
        "elements": [
          {
            "type": "pragma",
            "name": "^0.6.12",
            "source_mapping": {
              "start": 129,
              "length": 24,
              "filename_relative": "BOBAMASK.sol",
              "filename_absolute": "D:/CSE487 - PAPER/Dataset/raw_data/0x444fd826977d02a509c28d3cdfab853ac196199f/BOBAMASK.sol",
              "filename_short": "BOBAMASK.sol",
              "is_dependency": false,
              "lines": [
                23
              ],
              "starting_column": 1,
              "ending_column": 25
            },
            "type_specific_fields": {
              "directive": [
                "solidity",
                "^",
                "0.6",
                ".12"
              ]
            }
          }
        ],
        "description": "Version constraint ^0.6.12 contains known severe issues (https://solidity.readthedocs.io/en/latest/bugs.html)\n\t- FullInlinerNonExpressionSplitArgumentEvaluationOrder\n\t- MissingSideEffectsOnSelectorAccess\n\t- AbiReencodingHeadOverflowWithStaticArrayCleanup\n\t- DirtyBytesArrayToStorage\n\t- DataLocationChangeInInternalOverride\n\t- NestedCalldataArrayAbiReencodingSizeValidation\n\t- SignedImmutables\n\t- ABIDecodeTwoDimensionalArrayMemory\n\t- KeccakCaching\n\t- EmptyByteArrayCopy\n\t- DynamicArrayCleanup.\nIt is used by:\n\t- ^0.6.12 (BOBAMASK.sol#23)\n",
        "markdown": "Version constraint ^0.6.12 contains known severe issues (https://solidity.readthedocs.io/en/latest/bugs.html)\n\t- FullInlinerNonExpressionSplitArgumentEvaluationOrder\n\t- MissingSideEffectsOnSelectorAccess\n\t- AbiReencodingHeadOverflowWithStaticArrayCleanup\n\t- DirtyBytesArrayToStorage\n\t- DataLocationChangeInInternalOverride\n\t- NestedCalldataArrayAbiReencodingSizeValidation\n\t- SignedImmutables\n\t- ABIDecodeTwoDimensionalArrayMemory\n\t- KeccakCaching\n\t- EmptyByteArrayCopy\n\t- DynamicArrayCleanup.\nIt is used by:\n\t- [^0.6.12](BOBAMASK.sol#L23)\n",
        "first_markdown_element": "BOBAMASK.sol#L23",
        "id": "0cbb347744dd68077cfa60a70b35644fc88bad9789cbb795e6aded094b981a76",
        "check": "solc-version",
        "impact": "Informational",
        "confidence": "High"
      },
      {
        "elements": [],
        "description": "solc-0.6.12 is an outdated solc version. Use a more recent version (at least 0.8.0), if possible.\n",
        "markdown": "solc-0.6.12 is an outdated solc version. Use a more recent version (at least 0.8.0), if possible.\n",
        "first_markdown_element": "",
        "id": "dde195ef8d4d5c5489c6627531ef2ba10109e5f0768ce75d0cfbe826810ec83e",
        "check": "solc-version",
        "impact": "Informational",
        "confidence": "High"
      },
      {
        "elements": [
          {
            "type": "function",
            "name": "sendValue",
            "source_mapping": {
              "start": 1313,
              "length": 403,
              "filename_relative": "BOBAMASK.sol",
              "filename_absolute": "D:/CSE487 - PAPER/Dataset/raw_data/0x444fd826977d02a509c28d3cdfab853ac196199f/BOBAMASK.sol",
              "filename_short": "BOBAMASK.sol",
              "is_dependency": false,
              "lines": [
                85,
                86,
                87,
                88,
                89,
                90,
                91,
                92,
                93,
                94,
                95,
                96,
                97
              ],
              "starting_column": 5,
              "ending_column": 6
            },
            "type_specific_fields": {
              "parent": {
                "type": "contract",
                "name": "Address",
                "source_mapping": {
                  "start": 891,
                  "length": 2803,
                  "filename_relative": "BOBAMASK.sol",
                  "filename_absolute": "D:/CSE487 - PAPER/Dataset/raw_data/0x444fd826977d02a509c28d3cdfab853ac196199f/BOBAMASK.sol",
                  "filename_short": "BOBAMASK.sol",
                  "is_dependency": false,
                  "lines": [
                    65,
                    66,
                    67,
                    68,
                    69,
                    70,
                    71,
                    72,
                    73,
                    74,
                    75,
                    76,
                    77,
                    78,
                    79,
                    80,
                    81,
                    82,
                    83,
                    84,
                    85,
                    86,
                    87,
                    88,
                    89,
                    90,
                    91,
                    92,
                    93,
                    94,
                    95,
                    96,
                    97,
                    98,
                    99,
                    100,
                    101,
                    102,
                    103,
                    104,
                    105,
                    106,
                    107,
                    108,
                    109,
                    110,
                    111,
                    112,
                    113,
                    114,
                    115,
                    116,
                    117,
                    118,
                    119,
                    120,
                    121,
                    122,
                    123,
                    124,
                    125,
                    126,
                    127,
                    128,
                    129,
                    130,
                    131,
                    132,
                    133,
                    134,
                    135,
                    136,
                    137,
                    138,
                    139,
                    140,
                    141,
                    142,
                    143,
                    144,
                    145,
                    146,
                    147,
                    148,
                    149,
                    150,
                    151,
                    152,
                    153,
                    154,
                    155,
                    156,
                    157,
                    158,
                    159,
                    160,
                    161,
                    162,
                    163,
                    164,
                    165,
                    166,
                    167,
                    168,
                    169,
                    170,
                    171,
                    172,
                    173,
                    174,
                    175,
                    176,
                    177,
                    178,
                    179
                  ],
                  "starting_column": 1,
                  "ending_column": 2
                }
              },
              "signature": "sendValue(address,uint256)"
            }
          },
          {
            "type": "node",
            "name": "(success,None) = recipient.call{value: amount}()",
            "source_mapping": {
              "start": 1563,
              "length": 54,
              "filename_relative": "BOBAMASK.sol",
              "filename_absolute": "D:/CSE487 - PAPER/Dataset/raw_data/0x444fd826977d02a509c28d3cdfab853ac196199f/BOBAMASK.sol",
              "filename_short": "BOBAMASK.sol",
              "is_dependency": false,
              "lines": [
                93
              ],
              "starting_column": 9,
              "ending_column": 63
            },
            "type_specific_fields": {
              "parent": {
                "type": "function",
                "name": "sendValue",
                "source_mapping": {
                  "start": 1313,
                  "length": 403,
                  "filename_relative": "BOBAMASK.sol",
                  "filename_absolute": "D:/CSE487 - PAPER/Dataset/raw_data/0x444fd826977d02a509c28d3cdfab853ac196199f/BOBAMASK.sol",
                  "filename_short": "BOBAMASK.sol",
                  "is_dependency": false,
                  "lines": [
                    85,
                    86,
                    87,
                    88,
                    89,
                    90,
                    91,
                    92,
                    93,
                    94,
                    95,
                    96,
                    97
                  ],
                  "starting_column": 5,
                  "ending_column": 6
                },
                "type_specific_fields": {
                  "parent": {
                    "type": "contract",
                    "name": "Address",
                    "source_mapping": {
                      "start": 891,
                      "length": 2803,
                      "filename_relative": "BOBAMASK.sol",
                      "filename_absolute": "D:/CSE487 - PAPER/Dataset/raw_data/0x444fd826977d02a509c28d3cdfab853ac196199f/BOBAMASK.sol",
                      "filename_short": "BOBAMASK.sol",
                      "is_dependency": false,
                      "lines": [
                        65,
                        66,
                        67,
                        68,
                        69,
                        70,
                        71,
                        72,
                        73,
                        74,
                        75,
                        76,
                        77,
                        78,
                        79,
                        80,
                        81,
                        82,
                        83,
                        84,
                        85,
                        86,
                        87,
                        88,
                        89,
                        90,
                        91,
                        92,
                        93,
                        94,
                        95,
                        96,
                        97,
                        98,
                        99,
                        100,
                        101,
                        102,
                        103,
                        104,
                        105,
                        106,
                        107,
                        108,
                        109,
                        110,
                        111,
                        112,
                        113,
                        114,
                        115,
                        116,
                        117,
                        118,
                        119,
                        120,
                        121,
                        122,
                        123,
                        124,
                        125,
                        126,
                        127,
                        128,
                        129,
                        130,
                        131,
                        132,
                        133,
                        134,
                        135,
                        136,
                        137,
                        138,
                        139,
                        140,
                        141,
                        142,
                        143,
                        144,
                        145,
                        146,
                        147,
                        148,
                        149,
                        150,
                        151,
                        152,
                        153,
                        154,
                        155,
                        156,
                        157,
                        158,
                        159,
                        160,
                        161,
                        162,
                        163,
                        164,
                        165,
                        166,
                        167,
                        168,
                        169,
                        170,
                        171,
                        172,
                        173,
                        174,
                        175,
                        176,
                        177,
                        178,
                        179
                      ],
                      "starting_column": 1,
                      "ending_column": 2
                    }
                  },
                  "signature": "sendValue(address,uint256)"
                }
              }
            }
          }
        ],
        "description": "Low level call in Address.sendValue(address,uint256) (BOBAMASK.sol#85-97):\n\t- (success,None) = recipient.call{value: amount}() (BOBAMASK.sol#93)\n",
        "markdown": "Low level call in [Address.sendValue(address,uint256)](BOBAMASK.sol#L85-L97):\n\t- [(success,None) = recipient.call{value: amount}()](BOBAMASK.sol#L93)\n",
        "first_markdown_element": "BOBAMASK.sol#L85-L97",
        "id": "137ccd732cb3f8ac3ecaffe16ab5039cc8b5573afbc01b3ddfe6ee83846aaae8",
        "check": "low-level-calls",
        "impact": "Informational",
        "confidence": "High"
      },
      {
        "elements": [
          {
            "type": "function",
            "name": "_functionCallWithValue",
            "source_mapping": {
              "start": 2690,
              "length": 1000,
              "filename_relative": "BOBAMASK.sol",
              "filename_absolute": "D:/CSE487 - PAPER/Dataset/raw_data/0x444fd826977d02a509c28d3cdfab853ac196199f/BOBAMASK.sol",
              "filename_short": "BOBAMASK.sol",
              "is_dependency": false,
              "lines": [
                135,
                136,
                137,
                138,
                139,
                140,
                141,
                142,
                143,
                144,
                145,
                146,
                147,
                148,
                149,
                150,
                151,
                152,
                153,
                154,
                155,
                156,
                157,
                158,
                159,
                160,
                161,
                162,
                163,
                164,
                165,
                166,
                167,
                168,
                169,
                170,
                171,
                172,
                173,
                174,
                175,
                176,
                177
              ],
              "starting_column": 5,
              "ending_column": 6
            },
            "type_specific_fields": {
              "parent": {
                "type": "contract",
                "name": "Address",
                "source_mapping": {
                  "start": 891,
                  "length": 2803,
                  "filename_relative": "BOBAMASK.sol",
                  "filename_absolute": "D:/CSE487 - PAPER/Dataset/raw_data/0x444fd826977d02a509c28d3cdfab853ac196199f/BOBAMASK.sol",
                  "filename_short": "BOBAMASK.sol",
                  "is_dependency": false,
                  "lines": [
                    65,
                    66,
                    67,
                    68,
                    69,
                    70,
                    71,
                    72,
                    73,
                    74,
                    75,
                    76,
                    77,
                    78,
                    79,
                    80,
                    81,
                    82,
                    83,
                    84,
                    85,
                    86,
                    87,
                    88,
                    89,
                    90,
                    91,
                    92,
                    93,
                    94,
                    95,
                    96,
                    97,
                    98,
                    99,
                    100,
                    101,
                    102,
                    103,
                    104,
                    105,
                    106,
                    107,
                    108,
                    109,
                    110,
                    111,
                    112,
                    113,
                    114,
                    115,
                    116,
                    117,
                    118,
                    119,
                    120,
                    121,
                    122,
                    123,
                    124,
                    125,
                    126,
                    127,
                    128,
                    129,
                    130,
                    131,
                    132,
                    133,
                    134,
                    135,
                    136,
                    137,
                    138,
                    139,
                    140,
                    141,
                    142,
                    143,
                    144,
                    145,
                    146,
                    147,
                    148,
                    149,
                    150,
                    151,
                    152,
                    153,
                    154,
                    155,
                    156,
                    157,
                    158,
                    159,
                    160,
                    161,
                    162,
                    163,
                    164,
                    165,
                    166,
                    167,
                    168,
                    169,
                    170,
                    171,
                    172,
                    173,
                    174,
                    175,
                    176,
                    177,
                    178,
                    179
                  ],
                  "starting_column": 1,
                  "ending_column": 2
                }
              },
              "signature": "_functionCallWithValue(address,bytes,uint256,string)"
            }
          },
          {
            "type": "node",
            "name": "(success,returndata) = target.call{value: weiValue}(data)",
            "source_mapping": {
              "start": 2982,
              "length": 78,
              "filename_relative": "BOBAMASK.sol",
              "filename_absolute": "D:/CSE487 - PAPER/Dataset/raw_data/0x444fd826977d02a509c28d3cdfab853ac196199f/BOBAMASK.sol",
              "filename_short": "BOBAMASK.sol",
              "is_dependency": false,
              "lines": [
                143
              ],
              "starting_column": 9,
              "ending_column": 87
            },
            "type_specific_fields": {
              "parent": {
                "type": "function",
                "name": "_functionCallWithValue",
                "source_mapping": {
                  "start": 2690,
                  "length": 1000,
                  "filename_relative": "BOBAMASK.sol",
                  "filename_absolute": "D:/CSE487 - PAPER/Dataset/raw_data/0x444fd826977d02a509c28d3cdfab853ac196199f/BOBAMASK.sol",
                  "filename_short": "BOBAMASK.sol",
                  "is_dependency": false,
                  "lines": [
                    135,
                    136,
                    137,
                    138,
                    139,
                    140,
                    141,
                    142,
                    143,
                    144,
                    145,
                    146,
                    147,
                    148,
                    149,
                    150,
                    151,
                    152,
                    153,
                    154,
                    155,
                    156,
                    157,
                    158,
                    159,
                    160,
                    161,
                    162,
                    163,
                    164,
                    165,
                    166,
                    167,
                    168,
                    169,
                    170,
                    171,
                    172,
                    173,
                    174,
                    175,
                    176,
                    177
                  ],
                  "starting_column": 5,
                  "ending_column": 6
                },
                "type_specific_fields": {
                  "parent": {
                    "type": "contract",
                    "name": "Address",
                    "source_mapping": {
                      "start": 891,
                      "length": 2803,
                      "filename_relative": "BOBAMASK.sol",
                      "filename_absolute": "D:/CSE487 - PAPER/Dataset/raw_data/0x444fd826977d02a509c28d3cdfab853ac196199f/BOBAMASK.sol",
                      "filename_short": "BOBAMASK.sol",
                      "is_dependency": false,
                      "lines": [
                        65,
                        66,
                        67,
                        68,
                        69,
                        70,
                        71,
                        72,
                        73,
                        74,
                        75,
                        76,
                        77,
                        78,
                        79,
                        80,
                        81,
                        82,
                        83,
                        84,
                        85,
                        86,
                        87,
                        88,
                        89,
                        90,
                        91,
                        92,
                        93,
                        94,
                        95,
                        96,
                        97,
                        98,
                        99,
                        100,
                        101,
                        102,
                        103,
                        104,
                        105,
                        106,
                        107,
                        108,
                        109,
                        110,
                        111,
                        112,
                        113,
                        114,
                        115,
                        116,
                        117,
                        118,
                        119,
                        120,
                        121,
                        122,
                        123,
                        124,
                        125,
                        126,
                        127,
                        128,
                        129,
                        130,
                        131,
                        132,
                        133,
                        134,
                        135,
                        136,
                        137,
                        138,
                        139,
                        140,
                        141,
                        142,
                        143,
                        144,
                        145,
                        146,
                        147,
                        148,
                        149,
                        150,
                        151,
                        152,
                        153,
                        154,
                        155,
                        156,
                        157,
                        158,
                        159,
                        160,
                        161,
                        162,
                        163,
                        164,
                        165,
                        166,
                        167,
                        168,
                        169,
                        170,
                        171,
                        172,
                        173,
                        174,
                        175,
                        176,
                        177,
                        178,
                        179
                      ],
                      "starting_column": 1,
                      "ending_column": 2
                    }
                  },
                  "signature": "_functionCallWithValue(address,bytes,uint256,string)"
                }
              }
            }
          }
        ],
        "description": "Low level call in Address._functionCallWithValue(address,bytes,uint256,string) (BOBAMASK.sol#135-177):\n\t- (success,returndata) = target.call{value: weiValue}(data) (BOBAMASK.sol#143)\n",
        "markdown": "Low level call in [Address._functionCallWithValue(address,bytes,uint256,string)](BOBAMASK.sol#L135-L177):\n\t- [(success,returndata) = target.call{value: weiValue}(data)](BOBAMASK.sol#L143)\n",
        "first_markdown_element": "BOBAMASK.sol#L135-L177",
        "id": "e7f1b6d3feebe4af683ef77723e33fd1c06d460ce47a8c917b000865dfdfd3c2",
        "check": "low-level-calls",
        "impact": "Informational",
        "confidence": "High"
      },
      {
        "elements": [
          {
            "type": "node",
            "name": "this",
            "source_mapping": {
              "start": 5553,
              "length": 4,
              "filename_relative": "BOBAMASK.sol",
              "filename_absolute": "D:/CSE487 - PAPER/Dataset/raw_data/0x444fd826977d02a509c28d3cdfab853ac196199f/BOBAMASK.sol",
              "filename_short": "BOBAMASK.sol",
              "is_dependency": false,
              "lines": [
                305
              ],
              "starting_column": 9,
              "ending_column": 13
            },
            "type_specific_fields": {
              "parent": {
                "type": "function",
                "name": "_msgData",
                "source_mapping": {
                  "start": 5476,
                  "length": 236,
                  "filename_relative": "BOBAMASK.sol",
                  "filename_absolute": "D:/CSE487 - PAPER/Dataset/raw_data/0x444fd826977d02a509c28d3cdfab853ac196199f/BOBAMASK.sol",
                  "filename_short": "BOBAMASK.sol",
                  "is_dependency": false,
                  "lines": [
                    303,
                    304,
                    305,
                    306,
                    307,
                    308,
                    309
                  ],
                  "starting_column": 5,
                  "ending_column": 6
                },
                "type_specific_fields": {
                  "parent": {
                    "type": "contract",
                    "name": "Context",
                    "source_mapping": {
                      "start": 5317,
                      "length": 399,
                      "filename_relative": "BOBAMASK.sol",
                      "filename_absolute": "D:/CSE487 - PAPER/Dataset/raw_data/0x444fd826977d02a509c28d3cdfab853ac196199f/BOBAMASK.sol",
                      "filename_short": "BOBAMASK.sol",
                      "is_dependency": false,
                      "lines": [
                        291,
                        292,
                        293,
                        294,
                        295,
                        296,
                        297,
                        298,
                        299,
                        300,
                        301,
                        302,
                        303,
                        304,
                        305,
                        306,
                        307,
                        308,
                        309,
                        310,
                        311
                      ],
                      "starting_column": 1,
                      "ending_column": 2
                    }
                  },
                  "signature": "_msgData()"
                }
              }
            }
          },
          {
            "type": "contract",
            "name": "Context",
            "source_mapping": {
              "start": 5317,
              "length": 399,
              "filename_relative": "BOBAMASK.sol",
              "filename_absolute": "D:/CSE487 - PAPER/Dataset/raw_data/0x444fd826977d02a509c28d3cdfab853ac196199f/BOBAMASK.sol",
              "filename_short": "BOBAMASK.sol",
              "is_dependency": false,
              "lines": [
                291,
                292,
                293,
                294,
                295,
                296,
                297,
                298,
                299,
                300,
                301,
                302,
                303,
                304,
                305,
                306,
                307,
                308,
                309,
                310,
                311
              ],
              "starting_column": 1,
              "ending_column": 2
            }
          }
        ],
        "description": "Redundant expression \"this (BOBAMASK.sol#305)\" inContext (BOBAMASK.sol#291-311)\n",
        "markdown": "Redundant expression \"[this](BOBAMASK.sol#L305)\" in[Context](BOBAMASK.sol#L291-L311)\n",
        "first_markdown_element": "BOBAMASK.sol#L305",
        "id": "41f830206dc8b0a8bcdc6dd2ab7c03638f7bafa9d698555ef19fdc633d9a2cac",
        "check": "redundant-statements",
        "impact": "Informational",
        "confidence": "High"
      },
      {
        "elements": [
          {
            "type": "variable",
            "name": "_symbol",
            "source_mapping": {
              "start": 7124,
              "length": 31,
              "filename_relative": "BOBAMASK.sol",
              "filename_absolute": "D:/CSE487 - PAPER/Dataset/raw_data/0x444fd826977d02a509c28d3cdfab853ac196199f/BOBAMASK.sol",
              "filename_short": "BOBAMASK.sol",
              "is_dependency": false,
              "lines": [
                399
              ],
              "starting_column": 5,
              "ending_column": 36
            },
            "type_specific_fields": {
              "parent": {
                "type": "contract",
                "name": "BOBAMASK",
                "source_mapping": {
                  "start": 6746,
                  "length": 2871,
                  "filename_relative": "BOBAMASK.sol",
                  "filename_absolute": "D:/CSE487 - PAPER/Dataset/raw_data/0x444fd826977d02a509c28d3cdfab853ac196199f/BOBAMASK.sol",
                  "filename_short": "BOBAMASK.sol",
                  "is_dependency": false,
                  "lines": [
                    381,
                    382,
                    383,
                    384,
                    385,
                    386,
                    387,
                    388,
                    389,
                    390,
                    391,
                    392,
                    393,
                    394,
                    395,
                    396,
                    397,
                    398,
                    399,
                    400,
                    401,
                    402,
                    403,
                    404,
                    405,
                    406,
                    407,
                    408,
                    409,
                    410,
                    411,
                    412,
                    413,
                    414,
                    415,
                    416,
                    417,
                    418,
                    419,
                    420,
                    421,
                    422,
                    423,
                    424,
                    425,
                    426,
                    427,
                    428,
                    429,
                    430,
                    431,
                    432,
                    433,
                    434,
                    435,
                    436,
                    437,
                    438,
                    439,
                    440,
                    441,
                    442,
                    443,
                    444,
                    445,
                    446,
                    447,
                    448,
                    449,
                    450,
                    451,
                    452,
                    453,
                    454,
                    455,
                    456,
                    457,
                    458,
                    459,
                    460,
                    461,
                    462,
                    463,
                    464,
                    465,
                    466,
                    467,
                    468,
                    469,
                    470,
                    471,
                    472,
                    473,
                    474,
                    475,
                    476,
                    477,
                    478,
                    479,
                    480,
                    481,
                    482,
                    483,
                    484,
                    485,
                    486,
                    487,
                    488,
                    489,
                    490,
                    491,
                    492,
                    493,
                    494,
                    495,
                    496,
                    497,
                    498,
                    499,
                    500,
                    501,
                    502,
                    503,
                    504,
                    505,
                    506,
                    507,
                    508,
                    509,
                    510,
                    511,
                    512,
                    513,
                    514,
                    515,
                    516,
                    517,
                    518,
                    519,
                    520,
                    521,
                    522,
                    523,
                    524,
                    525,
                    526,
                    527,
                    528
                  ],
                  "starting_column": 1,
                  "ending_column": 0
                }
              }
            }
          }
        ],
        "description": "BOBAMASK._symbol (BOBAMASK.sol#399) should be constant \n",
        "markdown": "[BOBAMASK._symbol](BOBAMASK.sol#L399) should be constant \n",
        "first_markdown_element": "BOBAMASK.sol#L399",
        "id": "43d8450bd805adcd25c8557ff8c46e88720152874f468f862ed3dbebc3fa27a7",
        "check": "constable-states",
        "impact": "Optimization",
        "confidence": "High"
      },
      {
        "elements": [
          {
            "type": "variable",
            "name": "_tTotal",
            "source_mapping": {
              "start": 7023,
              "length": 45,
              "filename_relative": "BOBAMASK.sol",
              "filename_absolute": "D:/CSE487 - PAPER/Dataset/raw_data/0x444fd826977d02a509c28d3cdfab853ac196199f/BOBAMASK.sol",
              "filename_short": "BOBAMASK.sol",
              "is_dependency": false,
              "lines": [
                395
              ],
              "starting_column": 5,
              "ending_column": 50
            },
            "type_specific_fields": {
              "parent": {
                "type": "contract",
                "name": "BOBAMASK",
                "source_mapping": {
                  "start": 6746,
                  "length": 2871,
                  "filename_relative": "BOBAMASK.sol",
                  "filename_absolute": "D:/CSE487 - PAPER/Dataset/raw_data/0x444fd826977d02a509c28d3cdfab853ac196199f/BOBAMASK.sol",
                  "filename_short": "BOBAMASK.sol",
                  "is_dependency": false,
                  "lines": [
                    381,
                    382,
                    383,
                    384,
                    385,
                    386,
                    387,
                    388,
                    389,
                    390,
                    391,
                    392,
                    393,
                    394,
                    395,
                    396,
                    397,
                    398,
                    399,
                    400,
                    401,
                    402,
                    403,
                    404,
                    405,
                    406,
                    407,
                    408,
                    409,
                    410,
                    411,
                    412,
                    413,
                    414,
                    415,
                    416,
                    417,
                    418,
                    419,
                    420,
                    421,
                    422,
                    423,
                    424,
                    425,
                    426,
                    427,
                    428,
                    429,
                    430,
                    431,
                    432,
                    433,
                    434,
                    435,
                    436,
                    437,
                    438,
                    439,
                    440,
                    441,
                    442,
                    443,
                    444,
                    445,
                    446,
                    447,
                    448,
                    449,
                    450,
                    451,
                    452,
                    453,
                    454,
                    455,
                    456,
                    457,
                    458,
                    459,
                    460,
                    461,
                    462,
                    463,
                    464,
                    465,
                    466,
                    467,
                    468,
                    469,
                    470,
                    471,
                    472,
                    473,
                    474,
                    475,
                    476,
                    477,
                    478,
                    479,
                    480,
                    481,
                    482,
                    483,
                    484,
                    485,
                    486,
                    487,
                    488,
                    489,
                    490,
                    491,
                    492,
                    493,
                    494,
                    495,
                    496,
                    497,
                    498,
                    499,
                    500,
                    501,
                    502,
                    503,
                    504,
                    505,
                    506,
                    507,
                    508,
                    509,
                    510,
                    511,
                    512,
                    513,
                    514,
                    515,
                    516,
                    517,
                    518,
                    519,
                    520,
                    521,
                    522,
                    523,
                    524,
                    525,
                    526,
                    527,
                    528
                  ],
                  "starting_column": 1,
                  "ending_column": 0
                }
              }
            }
          }
        ],
        "description": "BOBAMASK._tTotal (BOBAMASK.sol#395) should be constant \n",
        "markdown": "[BOBAMASK._tTotal](BOBAMASK.sol#L395) should be constant \n",
        "first_markdown_element": "BOBAMASK.sol#L395",
        "id": "660a03141e5aa4b29d1d81d20996297bcee93af1bcf53e8ae8782a4a571380d7",
        "check": "constable-states",
        "impact": "Optimization",
        "confidence": "High"
      },
      {
        "elements": [
          {
            "type": "variable",
            "name": "_name",
            "source_mapping": {
              "start": 7076,
              "length": 39,
              "filename_relative": "BOBAMASK.sol",
              "filename_absolute": "D:/CSE487 - PAPER/Dataset/raw_data/0x444fd826977d02a509c28d3cdfab853ac196199f/BOBAMASK.sol",
              "filename_short": "BOBAMASK.sol",
              "is_dependency": false,
              "lines": [
                397
              ],
              "starting_column": 5,
              "ending_column": 44
            },
            "type_specific_fields": {
              "parent": {
                "type": "contract",
                "name": "BOBAMASK",
                "source_mapping": {
                  "start": 6746,
                  "length": 2871,
                  "filename_relative": "BOBAMASK.sol",
                  "filename_absolute": "D:/CSE487 - PAPER/Dataset/raw_data/0x444fd826977d02a509c28d3cdfab853ac196199f/BOBAMASK.sol",
                  "filename_short": "BOBAMASK.sol",
                  "is_dependency": false,
                  "lines": [
                    381,
                    382,
                    383,
                    384,
                    385,
                    386,
                    387,
                    388,
                    389,
                    390,
                    391,
                    392,
                    393,
                    394,
                    395,
                    396,
                    397,
                    398,
                    399,
                    400,
                    401,
                    402,
                    403,
                    404,
                    405,
                    406,
                    407,
                    408,
                    409,
                    410,
                    411,
                    412,
                    413,
                    414,
                    415,
                    416,
                    417,
                    418,
                    419,
                    420,
                    421,
                    422,
                    423,
                    424,
                    425,
                    426,
                    427,
                    428,
                    429,
                    430,
                    431,
                    432,
                    433,
                    434,
                    435,
                    436,
                    437,
                    438,
                    439,
                    440,
                    441,
                    442,
                    443,
                    444,
                    445,
                    446,
                    447,
                    448,
                    449,
                    450,
                    451,
                    452,
                    453,
                    454,
                    455,
                    456,
                    457,
                    458,
                    459,
                    460,
                    461,
                    462,
                    463,
                    464,
                    465,
                    466,
                    467,
                    468,
                    469,
                    470,
                    471,
                    472,
                    473,
                    474,
                    475,
                    476,
                    477,
                    478,
                    479,
                    480,
                    481,
                    482,
                    483,
                    484,
                    485,
                    486,
                    487,
                    488,
                    489,
                    490,
                    491,
                    492,
                    493,
                    494,
                    495,
                    496,
                    497,
                    498,
                    499,
                    500,
                    501,
                    502,
                    503,
                    504,
                    505,
                    506,
                    507,
                    508,
                    509,
                    510,
                    511,
                    512,
                    513,
                    514,
                    515,
                    516,
                    517,
                    518,
                    519,
                    520,
                    521,
                    522,
                    523,
                    524,
                    525,
                    526,
                    527,
                    528
                  ],
                  "starting_column": 1,
                  "ending_column": 0
                }
              }
            }
          }
        ],
        "description": "BOBAMASK._name (BOBAMASK.sol#397) should be constant \n",
        "markdown": "[BOBAMASK._name](BOBAMASK.sol#L397) should be constant \n",
        "first_markdown_element": "BOBAMASK.sol#L397",
        "id": "82f177ee37b555977f737e52434a32ff1c49057b7933c773a2e0e4d93e18ee24",
        "check": "constable-states",
        "impact": "Optimization",
        "confidence": "High"
      },
      {
        "elements": [
          {
            "type": "variable",
            "name": "_decimals",
            "source_mapping": {
              "start": 7164,
              "length": 28,
              "filename_relative": "BOBAMASK.sol",
              "filename_absolute": "D:/CSE487 - PAPER/Dataset/raw_data/0x444fd826977d02a509c28d3cdfab853ac196199f/BOBAMASK.sol",
              "filename_short": "BOBAMASK.sol",
              "is_dependency": false,
              "lines": [
                401
              ],
              "starting_column": 5,
              "ending_column": 33
            },
            "type_specific_fields": {
              "parent": {
                "type": "contract",
                "name": "BOBAMASK",
                "source_mapping": {
                  "start": 6746,
                  "length": 2871,
                  "filename_relative": "BOBAMASK.sol",
                  "filename_absolute": "D:/CSE487 - PAPER/Dataset/raw_data/0x444fd826977d02a509c28d3cdfab853ac196199f/BOBAMASK.sol",
                  "filename_short": "BOBAMASK.sol",
                  "is_dependency": false,
                  "lines": [
                    381,
                    382,
                    383,
                    384,
                    385,
                    386,
                    387,
                    388,
                    389,
                    390,
                    391,
                    392,
                    393,
                    394,
                    395,
                    396,
                    397,
                    398,
                    399,
                    400,
                    401,
                    402,
                    403,
                    404,
                    405,
                    406,
                    407,
                    408,
                    409,
                    410,
                    411,
                    412,
                    413,
                    414,
                    415,
                    416,
                    417,
                    418,
                    419,
                    420,
                    421,
                    422,
                    423,
                    424,
                    425,
                    426,
                    427,
                    428,
                    429,
                    430,
                    431,
                    432,
                    433,
                    434,
                    435,
                    436,
                    437,
                    438,
                    439,
                    440,
                    441,
                    442,
                    443,
                    444,
                    445,
                    446,
                    447,
                    448,
                    449,
                    450,
                    451,
                    452,
                    453,
                    454,
                    455,
                    456,
                    457,
                    458,
                    459,
                    460,
                    461,
                    462,
                    463,
                    464,
                    465,
                    466,
                    467,
                    468,
                    469,
                    470,
                    471,
                    472,
                    473,
                    474,
                    475,
                    476,
                    477,
                    478,
                    479,
                    480,
                    481,
                    482,
                    483,
                    484,
                    485,
                    486,
                    487,
                    488,
                    489,
                    490,
                    491,
                    492,
                    493,
                    494,
                    495,
                    496,
                    497,
                    498,
                    499,
                    500,
                    501,
                    502,
                    503,
                    504,
                    505,
                    506,
                    507,
                    508,
                    509,
                    510,
                    511,
                    512,
                    513,
                    514,
                    515,
                    516,
                    517,
                    518,
                    519,
                    520,
                    521,
                    522,
                    523,
                    524,
                    525,
                    526,
                    527,
                    528
                  ],
                  "starting_column": 1,
                  "ending_column": 0
                }
              }
            }
          }
        ],
        "description": "BOBAMASK._decimals (BOBAMASK.sol#401) should be constant \n",
        "markdown": "[BOBAMASK._decimals](BOBAMASK.sol#L401) should be constant \n",
        "first_markdown_element": "BOBAMASK.sol#L401",
        "id": "a92a65cd4c57cd2ef2af8a7a2f7926ec77e6aadf68e12db64db0f44638e265c4",
        "check": "constable-states",
        "impact": "Optimization",
        "confidence": "High"
      }
    ]
  }
}